<Properties StartupConfiguration="{437DFC9E-EDCA-4D2B-BA75-D47BB08B9C49}|Default">
  <MonoDevelop.Ide.DebuggingService.Breakpoints>
    <BreakpointStore />
  </MonoDevelop.Ide.DebuggingService.Breakpoints>
  <MonoDevelop.Ide.Workbench ActiveDocument="ChatApp.Api/Program.cs">
    <Files>
      <File FileName="ChatApp.Api/Controllers/ChatController.cs" Line="20" Column="32" />
      <File FileName="ChatApp.Api/Program.cs" Line="22" Column="22" />
    </Files>
    <Pads>
      <Pad Id="ProjectPad">
        <State name="__root__">
          <Node name="ChatApp.Api" expanded="True">
            <Node name="ChatApp.Api" expanded="True">
              <Node name="Controllers" expanded="True" />
              <Node name="Data" expanded="True" />
              <Node name="Models" expanded="True" />
            </Node>
          </Node>
        </State>
      </Pad>
      <Pad Id="MonoDevelop.Debugger.WatchPad">
        <State />
      </Pad>
    </Pads>
  </MonoDevelop.Ide.Workbench>
  <MonoDevelop.Ide.ItemProperties.ChatApp.Api PreferredExecutionTarget="/Applications/Google Chrome.app" />
  <MonoDevelop.Ide.DebuggingService.PinnedWatches />
  <MonoDevelop.Ide.Workspace ActiveConfiguration="Debug" />
  <MultiItemStartupConfigurations />
</Properties>